README.rst
setup.cfg
setup.py
tormon/__init__.py
tormon/run.py
tormon.egg-info/PKG-INFO
tormon.egg-info/SOURCES.txt
tormon.egg-info/dependency_links.txt
tormon.egg-info/entry_points.txt
tormon.egg-info/not-zip-safe
tormon.egg-info/requires.txt
tormon.egg-info/top_level.txt
tormon/api/__init__.py
tormon/api/urls.py
tormon/api/utils.py
tormon/api/views.py
tormon/monitor/__init__.py
tormon/monitor/client.py
tormon/monitor/exceptions.py
tormon/monitor/readers.py
tormon/monitor/utils.py
tormon/monitor/writers.py
tormon/web/__init__.py
tormon/web/urls.py
tormon/web/views.py