Metadata-Version: 1.1
Name: tormon
Version: 0.0.11
Summary: Tornado based application monitor
Home-page: https://github.com/jnosal/tormon
Author: jnosal
Author-email: jacek.nosal@outlook.com
License: UNKNOWN
Keywords: tornado,redis,tormon
Platform: UNKNOWN
Classifier: Development Status :: 1 - Planning
Classifier: Intended Audience :: Developers
Classifier: Natural Language :: English
Classifier: License :: OSI Approved :: MIT License
Classifier: Operating System :: OS Independent
Classifier: Programming Language :: Python
Classifier: Programming Language :: Python :: 2
Classifier: Programming Language :: Python :: 2.6
Classifier: Programming Language :: Python :: 2.7
Classifier: Topic :: Software Development :: Libraries :: Python Modules
